{"date": 1647534602.350765, "list": [{"page": "http://goskomzemdnr.ru", "st": 0, "cs": 0, "protect": null}, {"page": "https://yaplakal.com", "st": 1, "cs": 2.05, "protect": "cloudflare"}, {"page": "https://kp.ru", "st": 0, "cs": 0, "protect": null}, {"page": "https://mir-lug.info", "st": 1, "cs": 6.48, "protect": "cloudflare"}, {"page": "https://pikabu.ru", "st": 1, "cs": 6.47, "protect": "cloudflare"}, {"page": "https://novochgrad.ru", "st": 0, "cs": 0, "protect": null}, {"page": "https://www.dpd.ru", "st": 1, "cs": 14.26, "protect": "nginx"}, {"page": "https://bank24.gosbank.su", "st": 0, "cs": 0, "protect": null}, {"page": "https://luganskgaz.org", "st": 1, "cs": 10.53, "protect": "nginx"}, {"page": "https://russian.rt.com", "st": 0, "cs": 0, "protect": null}, {"page": "https://www.lugvoda.com", "st": 1, "cs": 37.96, "protect": "nginx"}, {"page": "https://ren.tv", "st": 1, "cs": 8.21, "protect": "ddos-guard"}, {"page": "https://lnr.today", "st": 0, "cs": 0, "protect": null}, {"page": "https://rostelecom.ru", "st": 0, "cs": 0, "protect": null}, {"page": "https://mk.ru", "st": 0, "cs": 0, "protect": null}, {"page": "https://dnr24.su", "st": 1, "cs": 1.71, "protect": "cloudflare"}, {"page": "http://www.belinfonalog.ru", "st": 0, "cs": 0, "protect": null}, {"page": "https://lugaland.com", "st": 0, "cs": 0, "protect": null}, {"page": "http://guprec.ru", "st": 0, "cs": 0, "protect": null}, {"page": "https://miaistok.su", "st": 0, "cs": 0, "protect": null}, {"page": "https://svpressa.ru", "st": 0, "cs": 0, "protect": null}, {"page": "http://rtr-planeta.com", "st": 0, "cs": 0, "protect": null}, {"page": "http://mdsdnr.ru", "st": 0, "cs": 0, "protect": null}, {"page": "https://apps.sberbank.ru", "st": 0, "cs": 0, "protect": null}, {"page": "https://www.yaplakal.com", "st": 1, "cs": 6.6, "protect": "cloudflare"}, {"page": "https://crb-dnr.ru", "st": 0, "cs": 0, "protect": null}, {"page": "https://www.bryanskobl.ru", "st": 0, "cs": 0, "protect": null}, {"page": "http://khartsyzsk.ugletele.com", "st": 0, "cs": 0, "protect": null}, {"page": "https://xn----etbafsqscydaxc.xn--p1acf", "st": 0, "cs": 0, "protect": null}, {"page": "https://www.vedomosti.ru", "st": 0, "cs": 0, "protect": null}, {"page": "https://xn----7sbyb2abcjdpdb2a.xn--p1acf", "st": 0, "cs": 0, "protect": null}, {"page": "https://digitalrussia.tv", "st": 0, "cs": 0, "protect": null}, {"page": "https://e-trust.gosuslugi.ru", "st": 0, "cs": 0, "protect": null}, {"page": "https://malahov-pryamoj-efir.lol", "st": 0, "cs": 0, "protect": null}, {"page": "https://www.aerodar.ru", "st": 0, "cs": 0, "protect": null}, {"page": "http://smotrim.ru", "st": 0, "cs": 0, "protect": null}, {"page": "https://kirovreg.ru", "st": 0, "cs": 0, "protect": null}, {"page": "https://boxberry.ru", "st": 0, "cs": 0, "protect": null}, {"page": "https://lv.sputniknews.ru", "st": 0, "cs": 0, "protect": null}, {"page": "https://rbc.ru", "st": 0, "cs": 0, "protect": null}, {"page": "https://xn--b1akbpgy3fwa.xn--p1acf", "st": 0, "cs": 0, "protect": null}, {"page": "https://del-ko.ru", "st": 0, "cs": 0, "protect": null}, {"page": "http://www.tinkoff.ru", "st": 0, "cs": 0, "protect": null}, {"page": "https://datrans.ru", "st": 0, "cs": 0, "protect": null}, {"page": "https://newsua.ru", "st": 0, "cs": 0, "protect": null}, {"page": "http://novoaz-adm.3dn.ru", "st": 0, "cs": 0, "protect": null}, {"page": "https://kommersant.ru", "st": 0, "cs": 0, "protect": null}, {"page": "https://www.mil.by", "st": 0, "cs": 0, "protect": null}, {"page": "https://blackpantera.ru", "st": 0, "cs": 0, "protect": null}, {"page": "https://lgaki.info", "st": 0, "cs": 0, "protect": null}, {"page": "https://ria.ru", "st": 0, "cs": 0, "protect": null}, {"page": "https://mil.ru", "st": 0, "cs": 0, "protect": null}, {"page": "https://www.slonves.by", "st": 0, "cs": 0, "protect": null}, {"page": "https://dvinaland.ru", "st": 0, "cs": 0, "protect": null}, {"page": "https://www.povoz.ru", "st": 0, "cs": 0, "protect": null}, {"page": "https://riafan.ru", "st": 0, "cs": 0, "protect": null}, {"page": "http://www.nso.ru", "st": 0, "cs": 0, "protect": null}, {"page": "http://gum-centr.su", "st": 0, "cs": 0, "protect": null}, {"page": "https://lug-info.com", "st": 0, "cs": 0, "protect": null}, {"page": "http://gkecopoldnr.ru", "st": 0, "cs": 0, "protect": null}, {"page": "https://postdonbass.com", "st": 0, "cs": 0, "protect": null}, {"page": "https://perevozka-konteinerov.ru", "st": 0, "cs": 0, "protect": null}, {"page": "https://zarya.by", "st": 0, "cs": 0, "protect": null}, {"page": "https://www.dstu.education", "st": 0, "cs": 0, "protect": null}, {"page": "http://www.ucpir.ru", "st": 0, "cs": 0, "protect": null}, {"page": "https://www.lugenergo.ru", "st": 0, "cs": 0, "protect": null}, {"page": "https://lenobl.ru", "st": 0, "cs": 0, "protect": null}, {"page": "https://online.sberbank.ru", "st": 1, "cs": 0.56, "protect": ""}, {"page": "https://aif.ru", "st": 0, "cs": 0, "protect": null}, {"page": "https://mgb-dnr.ru", "st": 0, "cs": 0, "protect": null}, {"page": "https://dnr24.com", "st": 0, "cs": 0, "protect": null}, {"page": "http://bestmt.ru", "st": 0, "cs": 0, "protect": null}, {"page": "https://volgoduma.ru", "st": 0, "cs": 0, "protect": null}, {"page": "https://kursk.ru", "st": 0, "cs": 0, "protect": null}, {"page": "https://gov-murman.ru", "st": 0, "cs": 0, "protect": null}, {"page": "https://tass.ru", "st": 0, "cs": 0, "protect": null}, {"page": "https://lib-lg.com", "st": 0, "cs": 0, "protect": null}, {"page": "https://pwd.wto.economy.gov.ru", "st": 0, "cs": 0, "protect": null}, {"page": "https://dontr.ru", "st": 0, "cs": 0, "protect": null}, {"page": "https://moslenta.ru", "st": 0, "cs": 0, "protect": null}, {"page": "https://www.mashandling.ru", "st": 0, "cs": 0, "protect": null}, {"page": "http://pskov.ru", "st": 0, "cs": 0, "protect": null}, {"page": "http://kremlin.ru", "st": 0, "cs": 0, "protect": null}, {"page": "https://bestmt.ru", "st": 0, "cs": 0, "protect": null}, {"page": "https://dnrexport.ru", "st": 0, "cs": 0, "protect": null}, {"page": "https://xn--b1aea3ais.xn--p1acf", "st": 0, "cs": 0, "protect": null}, {"page": "https://regnum.ru", "st": 0, "cs": 0, "protect": null}, {"page": "https://xn--h1aheeehel.xn--p1acf", "st": 0, "cs": 0, "protect": null}, {"page": "https://belregion.ru", "st": 0, "cs": 0, "protect": null}, {"page": "https://ruform.ru", "st": 0, "cs": 0, "protect": null}, {"page": "http://wlad.eu", "st": 0, "cs": 0, "protect": null}, {"page": "http://lenta.ru", "st": 0, "cs": 0, "protect": null}, {"page": "https://www.nalog.gov.ru", "st": 0, "cs": 0, "protect": null}, {"page": "http://dokuchaevskga.ucoz.org", "st": 0, "cs": 0, "protect": null}, {"page": "https://www.lugmedpharm.su", "st": 0, "cs": 0, "protect": null}, {"page": "https://tranzit-auto.ru", "st": 0, "cs": 0, "protect": null}, {"page": "https://tpplnr.ru", "st": 1, "cs": 2.0, "protect": "cloudflare"}, {"page": "https://eurasia.expert", "st": 0, "cs": 0, "protect": null}, {"page": "https://xn----7sb3aecmcv8d.xn--p1ai", "st": 0, "cs": 0, "protect": null}, {"page": "https://trasko.ru", "st": 0, "cs": 0, "protect": null}, {"page": "http://magistrans.ru", "st": 0, "cs": 0, "protect": null}, {"page": "https://www.fontanka.ru", "st": 0, "cs": 0, "protect": null}, {"page": "http://mintek-dnr.ru", "st": 0, "cs": 0, "protect": null}, {"page": "http://druss.ru", "st": 0, "cs": 0, "protect": null}, {"page": "https://www.dentro.ru", "st": 0, "cs": 0, "protect": null}, {"page": "https://www.baikalsr.ru", "st": 1, "cs": 2.85, "protect": "rdwr"}, {"page": "https://proverki.gov.ru", "st": 0, "cs": 0, "protect": null}, {"page": "http://fpdnr.ru", "st": 0, "cs": 0, "protect": null}, {"page": "https://123789.ru", "st": 1, "cs": 1.62, "protect": "cloudflare"}, {"page": "https://www.sogruz.ru", "st": 1, "cs": 27.09, "protect": "nginx"}, {"page": "https://alfaradio.by", "st": 0, "cs": 0, "protect": null}, {"page": "http://izhtender.ru", "st": 0, "cs": 0, "protect": null}, {"page": "https://kurganobl.ru", "st": 0, "cs": 0, "protect": null}, {"page": "http://www.ctv.by", "st": 0, "cs": 0, "protect": null}, {"page": "https://don24.ru", "st": 1, "cs": 24.21, "protect": "nginx"}, {"page": "https://pfr.gov.ru", "st": 0, "cs": 0, "protect": null}, {"page": "https://mogilevnews.by", "st": 0, "cs": 0, "protect": null}, {"page": "https://info-portal.com.ru", "st": 0, "cs": 0, "protect": null}, {"page": "https://pochta-lnr.ru", "st": 0, "cs": 0, "protect": null}, {"page": "http://www.ivanovoobl.ru", "st": 0, "cs": 0, "protect": null}, {"page": "https://mosreg.ru", "st": 0, "cs": 0, "protect": null}, {"page": "https://grodnonews.by", "st": 0, "cs": 0, "protect": null}, {"page": "https://www.fesco.ru", "st": 0, "cs": 0, "protect": null}, {"page": "https://www.mos.ru/uslugi", "st": 0, "cs": 0, "protect": null}, {"page": "http://mcxdnr.ru", "st": 0, "cs": 0, "protect": null}, {"page": "https://dni.ru", "st": 0, "cs": 0, "protect": null}, {"page": "https://garant-logistika.ru", "st": 0, "cs": 0, "protect": null}, {"page": "https://www.cityexpress.ru", "st": 0, "cs": 0, "protect": null}, {"page": "http://gkgtn.ru", "st": 1, "cs": 8.21, "protect": "ddos-guard"}, {"page": "https://newsvideo.su/ru", "st": 0, "cs": 0, "protect": null}, {"page": "http://www.ria.ru", "st": 0, "cs": 0, "protect": null}, {"page": "https://pecom.ru", "st": 0, "cs": 0, "protect": null}, {"page": "https://www.dellin.ru", "st": 0, "cs": 0, "protect": null}, {"page": "https://mvd.gov.ru", "st": 0, "cs": 0, "protect": null}, {"page": "http://www.astralnalog.ru", "st": 0, "cs": 0, "protect": null}, {"page": "https://radiomir.by", "st": 0, "cs": 0, "protect": null}, {"page": "https://dnr-live.ru", "st": 1, "cs": 21.9, "protect": "nginx"}, {"page": "https://www.ponyexpress.ru", "st": 0, "cs": 0, "protect": null}, {"page": "https://oooyata.ru", "st": 1, "cs": 34.81, "protect": "nginx"}, {"page": "https://customs.gov.ru", "st": 0, "cs": 0, "protect": null}, {"page": "https://mvdlnr.ru", "st": 0, "cs": 0, "protect": null}, {"page": "http://alchevsk.su", "st": 0, "cs": 0, "protect": null}, {"page": "https://www.belnovosti.by", "st": 0, "cs": 0, "protect": null}, {"page": "http://lugansk.online", "st": 0, "cs": 0, "protect": null}, {"page": "https://stroi.gov.ru", "st": 0, "cs": 0, "protect": null}, {"page": "https://topwar.ru", "st": 1, "cs": 6.43, "protect": "cloudflare"}, {"page": "https://radiusfm.by", "st": 0, "cs": 0, "protect": null}, {"page": "https://radiostalica.by", "st": 0, "cs": 0, "protect": null}, {"page": "https://donmarkets.ru", "st": 0, "cs": 0, "protect": null}, {"page": "https://lnr.media", "st": 0, "cs": 0, "protect": null}, {"page": "https://omskportal.ru", "st": 0, "cs": 0, "protect": null}, {"page": "https://rynkilnr.su", "st": 0, "cs": 0, "protect": null}, {"page": "https://pre.admoblkaluga.ru", "st": 0, "cs": 0, "protect": null}, {"page": "http://rst-dnr.ru", "st": 0, "cs": 0, "protect": null}, {"page": "http://government.ru", "st": 0, "cs": 0, "protect": null}, {"page": "https://astrobl.ru", "st": 0, "cs": 0, "protect": null}, {"page": "https://www.vsoloviev.ru", "st": 0, "cs": 0, "protect": null}, {"page": "https://mail.rkn.gov.ru", "st": 0, "cs": 0, "protect": null}, {"page": "https://gtrklnr.com", "st": 0, "cs": 0, "protect": null}, {"page": "https://www.govvrn.ru", "st": 0, "cs": 0, "protect": null}, {"page": "https://trcont.com", "st": 0, "cs": 0, "protect": null}, {"page": "https://kk.bank/UdTs", "st": 0, "cs": 0, "protect": null}, {"page": "https://rutube.ru", "st": 0, "cs": 0, "protect": null}, {"page": "https://smi2.ru", "st": 0, "cs": 0, "protect": null}, {"page": "https://minpromlnr.su/main.php?start&deystvie=1", "st": 0, "cs": 0, "protect": null}, {"page": "http://gov39.ru", "st": 0, "cs": 0, "protect": null}, {"page": "https://www.gazeta.ru", "st": 1, "cs": 133.28, "protect": "QRATOR"}, {"page": "https://rg.ru", "st": 0, "cs": 0, "protect": null}, {"page": "http://mincult.govdnr.ru", "st": 0, "cs": 0, "protect": null}, {"page": "https://minstroy-dnr.ru", "st": 0, "cs": 0, "protect": null}, {"page": "https://minfindnr.ru", "st": 0, "cs": 0, "protect": null}, {"page": "https://radiobrestfm.by", "st": 0, "cs": 0, "protect": null}, {"page": "http://dnmchs.ru", "st": 0, "cs": 0, "protect": null}, {"page": "http://donmintrans.ru", "st": 0, "cs": 0, "protect": null}, {"page": "https://www.vesti.ru", "st": 0, "cs": 0, "protect": null}, {"page": "http://mgblnr.org", "st": 0, "cs": 0, "protect": null}, {"page": "https://ru-dostavka.ru", "st": 0, "cs": 0, "protect": null}, {"page": "https://itecorp.ru", "st": 0, "cs": 0, "protect": null}, {"page": "https://www.flagmanamur.ru", "st": 0, "cs": 0, "protect": null}, {"page": "https://www.tvrmogilev.by", "st": 0, "cs": 0, "protect": null}, {"page": "https://ako.ru", "st": 0, "cs": 0, "protect": null}, {"page": "http://armiyadnr.su", "st": 0, "cs": 0, "protect": null}, {"page": "http://saratov.gov.ru", "st": 0, "cs": 0, "protect": null}, {"page": "https://pgk.ru", "st": 0, "cs": 0, "protect": null}, {"page": "http://lgpu.org", "st": 0, "cs": 0, "protect": null}, {"page": "https://lugpost.ru", "st": 0, "cs": 0, "protect": null}, {"page": "https://avo.ru", "st": 0, "cs": 0, "protect": null}, {"page": "http://sztcom.ru", "st": 0, "cs": 0, "protect": null}, {"page": "https://xn--c1aeaazcckr9ah.xn--p1acf", "st": 0, "cs": 0, "protect": null}, {"page": "http://pravo.minjust.ru", "st": 0, "cs": 0, "protect": null}, {"page": "https://kubantv.ru", "st": 1, "cs": 8.21, "protect": "ddos-guard"}, {"page": "http://voroshilovka.ru", "st": 0, "cs": 0, "protect": null}, {"page": "https://xn--80aacoonefzg3am8b1fsb.xn--p1ai", "st": 0, "cs": 0, "protect": null}, {"page": "http://gorod-donetsk.com", "st": 0, "cs": 0, "protect": null}, {"page": "http://mashprocess.ru", "st": 0, "cs": 0, "protect": null}, {"page": "https://russian-center.ru", "st": 0, "cs": 0, "protect": null}, {"page": "http://gplnr.su", "st": 0, "cs": 0, "protect": null}, {"page": "https://www.tinkoff.ru", "st": 0, "cs": 0, "protect": null}, {"page": "http://zdravdnr.ru", "st": 0, "cs": 0, "protect": null}, {"page": "https://gazeta.ru", "st": 0, "cs": 0, "protect": null}, {"page": "https://rusmk.ru", "st": 0, "cs": 0, "protect": null}, {"page": "https://lugacom.com", "st": 0, "cs": 0, "protect": null}, {"page": "http://merlnr.su/news", "st": 0, "cs": 0, "protect": null}, {"page": "https://amulnr.wixsite.com/amulnr", "st": 1, "cs": 91.43, "protect": "Pepyaka/1.19.10"}, {"page": "https://minsknews.by", "st": 0, "cs": 0, "protect": null}, {"page": "https://mil-lnr.su", "st": 0, "cs": 0, "protect": null}, {"page": "https://3mob.ru", "st": 0, "cs": 0, "protect": null}, {"page": "https://fplnr.ru", "st": 0, "cs": 0, "protect": null}, {"page": "https://cloud.rkn.gov.ru", "st": 0, "cs": 0, "protect": null}, {"page": "https://hermitagemuseum.ru", "st": 0, "cs": 0, "protect": null}, {"page": "https://www.49gov.ru", "st": 0, "cs": 0, "protect": null}, {"page": "https://bezformata.com", "st": 0, "cs": 0, "protect": null}, {"page": "https://www.novreg.ru", "st": 0, "cs": 0, "protect": null}, {"page": "https://www.donland.ru", "st": 0, "cs": 0, "protect": null}, {"page": "https://uc-osnovanie.ru", "st": 0, "cs": 0, "protect": null}, {"page": "http://drkm-dnr.ru", "st": 0, "cs": 0, "protect": null}, {"page": "http://www.e-portal.ru", "st": 0, "cs": 0, "protect": null}, {"page": "http://parlament-novorossii.ru", "st": 0, "cs": 0, "protect": null}, {"page": "https://minobr.su", "st": 0, "cs": 0, "protect": null}, {"page": "https://uinlnr.su", "st": 0, "cs": 0, "protect": null}, {"page": "https://sber.ru", "st": 0, "cs": 0, "protect": null}, {"page": "https://kaznalnr.ru", "st": 0, "cs": 0, "protect": null}, {"page": "https://rkn.gov.ru", "st": 0, "cs": 0, "protect": null}, {"page": "https://stolica-s.su", "st": 0, "cs": 0, "protect": null}, {"page": "https://tk-kit.com", "st": 0, "cs": 0, "protect": null}, {"page": "https://radiobelarus.by", "st": 0, "cs": 0, "protect": null}, {"page": "https://www.skif-cargo.ru", "st": 1, "cs": 14.57, "protect": "cloudflare"}, {"page": "https://xn--d1achldmtc.xn--p1ai", "st": 0, "cs": 0, "protect": null}, {"page": "https://nordw.ru", "st": 1, "cs": 12.3, "protect": "QRATOR"}, {"page": "https://nrg-tk.ru", "st": 0, "cs": 0, "protect": null}, {"page": "https://www.company.rt.ru", "st": 0, "cs": 0, "protect": null}, {"page": "https://irkobl.ru", "st": 0, "cs": 0, "protect": null}, {"page": "http://phoenix-dnr.ru", "st": 0, "cs": 0, "protect": null}, {"page": "https://www.amurobl.ru", "st": 0, "cs": 0, "protect": null}, {"page": "http://guprsk.ru", "st": 0, "cs": 0, "protect": null}, {"page": "https://www.government-nnov.ru", "st": 0, "cs": 0, "protect": null}]}