{"date": 1648032298.632266, "list": [{"page": "https://e-trust.gosuslugi.ru", "st": 1, "cs": 0.08, "protect": ""}, {"page": "https://piwik-gosbar.gosuslugi.ru", "st": 0, "cs": 0, "protect": null}, {"page": "http://www.mjkx.gov.by", "st": 1, "cs": 0.6, "protect": "Beaver"}, {"page": "http://gpk.gov.by", "st": 1, "cs": 5.63, "protect": "cloudflare"}, {"page": "https://ssp.gosuslugi.ru", "st": 0, "cs": 0, "protect": null}, {"page": "https://cdn25.img.ria.ru", "st": 0, "cs": 0, "protect": null}, {"page": "https://pay.gosuslugi.ru", "st": 1, "cs": 0.02, "protect": "nginx"}, {"page": "https://esnsi.gosuslugi.ru", "st": 0, "cs": 0, "protect": null}, {"page": "https://oldimg.ria.ru", "st": 0, "cs": 0, "protect": null}, {"page": "https://culture.gosuslugi.ru", "st": 0, "cs": 0, "protect": null}, {"page": "http://www.rec.gov.by", "st": 1, "cs": 0.6, "protect": "Beaver"}, {"page": "https://posobie2020.gosuslugi.ru", "st": 0, "cs": 0, "protect": null}, {"page": "https://skuf-portal.gosuslugi.ru", "st": 0, "cs": 0, "protect": null}, {"page": "http://center.gov.by", "st": 1, "cs": 5.63, "protect": "cloudflare"}, {"page": "http://www.gki.gov.by/ru", "st": 1, "cs": 0.6, "protect": "Beaver"}, {"page": "https://en.ria.ru", "st": 0, "cs": 0, "protect": null}, {"page": "https://cdn3.img.ria.ru", "st": 0, "cs": 0, "protect": null}, {"page": "https://euro2020.ria.ru", "st": 0, "cs": 0, "protect": null}, {"page": "https://new.gosuslugi.ru", "st": 0, "cs": 0, "protect": null}, {"page": "https://www.amia.by", "st": 0, "cs": 0, "protect": null}, {"page": "https://www.minfin.gov.by", "st": 1, "cs": 61.22, "protect": "Microsoft-IIS/8.5"}, {"page": "http://www.customs.gov.by", "st": 1, "cs": 0.6, "protect": "Beaver"}, {"page": "https://sreda.dom.gosuslugi.ru", "st": 0, "cs": 0, "protect": null}, {"page": "https://static.gosuslugi.ru", "st": 0, "cs": 0, "protect": null}, {"page": "https://mvd.gov.ru", "st": 0, "cs": 0, "protect": null}, {"page": "http://www.gknt.gov.by", "st": 1, "cs": 0.6, "protect": "Beaver"}, {"page": "http://minprom.gov.by", "st": 1, "cs": 0.6, "protect": "Beaver"}, {"page": "https://cdn24.img.ria.ru", "st": 0, "cs": 0, "protect": null}, {"page": "http://www.kgb.by", "st": 1, "cs": 5.63, "protect": "cloudflare"}, {"page": "https://cdn21.img.ria.ru", "st": 0, "cs": 0, "protect": null}, {"page": "https://cdndc.img.ria.ru", "st": 0, "cs": 0, "protect": null}, {"page": "https://mvd.gov.by", "st": 0, "cs": 0, "protect": null}, {"page": "https://www.mlh.by", "st": 0, "cs": 0, "protect": null}, {"page": "https://guides.gosuslugi.ru", "st": 0, "cs": 0, "protect": null}, {"page": "http://belarp.by", "st": 1, "cs": 5.62, "protect": "cloudflare"}, {"page": "https://ervk.gosuslugi.ru", "st": 0, "cs": 0, "protect": null}, {"page": "https://techportal.gosuslugi.ru", "st": 0, "cs": 0, "protect": null}, {"page": "https://crimea.ria.ru", "st": 0, "cs": 0, "protect": null}, {"page": "https://mobileimg.img.ria.ru", "st": 0, "cs": 0, "protect": null}, {"page": "https://fileria1.video.ria.ru", "st": 0, "cs": 0, "protect": null}, {"page": "https://do.gosuslugi.ru", "st": 0, "cs": 0, "protect": null}, {"page": "https://edu.gov.by", "st": 0, "cs": 0, "protect": null}, {"page": "https://minpriroda.gov.by/ru", "st": 0, "cs": 0, "protect": null}, {"page": "https://partners.gosuslugi.ru", "st": 0, "cs": 0, "protect": null}, {"page": "http://kultura.by", "st": 1, "cs": 5.63, "protect": "cloudflare"}, {"page": "http://region.grodno.by", "st": 0, "cs": 0, "protect": null}, {"page": "https://belarus21.by", "st": 0, "cs": 0, "protect": null}, {"page": "https://cis.minsk.by", "st": 0, "cs": 0, "protect": null}, {"page": "https://frgu.gosuslugi.ru", "st": 0, "cs": 0, "protect": null}, {"page": "https://breathe.ria.ru", "st": 0, "cs": 0, "protect": null}, {"page": "https://rkn.gov.ru", "st": 1, "cs": 33.46, "protect": "nginx"}, {"page": "https://vitebsk-region.gov.by", "st": 0, "cs": 0, "protect": null}, {"page": "https://m.crimea.ria.ru", "st": 0, "cs": 0, "protect": null}, {"page": "https://regbusiness.gosuslugi.ru", "st": 0, "cs": 0, "protect": null}, {"page": "https://pos.gosuslugi.ru", "st": 0, "cs": 0, "protect": null}, {"page": "http://www.pravo.by", "st": 1, "cs": 5.63, "protect": "cloudflare"}, {"page": "https://info.gosuslugi.ru", "st": 0, "cs": 0, "protect": null}, {"page": "https://proverki.gov.ru", "st": 0, "cs": 0, "protect": null}, {"page": "http://mvd.gov.by", "st": 1, "cs": 5.63, "protect": "cloudflare"}, {"page": "http://www.bellesbumprom.by/ru", "st": 1, "cs": 5.66, "protect": "cloudflare"}, {"page": "http://www.mininform.gov.by", "st": 1, "cs": 5.66, "protect": "cloudflare"}, {"page": "https://nalog.gov.by", "st": 0, "cs": 0, "protect": null}, {"page": "https://api.dom.gosuslugi.ru", "st": 0, "cs": 0, "protect": null}, {"page": "https://lk.dom.gosuslugi.ru", "st": 0, "cs": 0, "protect": null}, {"page": "https://vak.gov.by", "st": 0, "cs": 0, "protect": null}, {"page": "https://stroi.gov.ru", "st": 0, "cs": 0, "protect": null}, {"page": "https://torgi-demo1.gosuslugi.ru", "st": 0, "cs": 0, "protect": null}, {"page": "https://cdn5.img.ria.ru", "st": 0, "cs": 0, "protect": null}, {"page": "https://cdn4.img.ria.ru", "st": 0, "cs": 0, "protect": null}, {"page": "https://cdnn2.img.ria.ru", "st": 0, "cs": 0, "protect": null}, {"page": "https://www.belstat.gov.by", "st": 0, "cs": 0, "protect": null}, {"page": "https://oldimg1.ria.ru", "st": 0, "cs": 0, "protect": null}, {"page": "https://radiosputnik.ria.ru", "st": 0, "cs": 0, "protect": null}, {"page": "https://autodiscover.ria.ru", "st": 0, "cs": 0, "protect": null}, {"page": "https://cdn22.img.ria.ru", "st": 0, "cs": 0, "protect": null}, {"page": "https://minsk-region.gov.by", "st": 0, "cs": 0, "protect": null}, {"page": "http://www.economy.gov.by", "st": 1, "cs": 0.6, "protect": "Beaver"}, {"page": "https://smev.gosuslugi.ru", "st": 0, "cs": 0, "protect": null}, {"page": "https://mvd-din.by", "st": 0, "cs": 0, "protect": null}, {"page": "http://nasb.gov.by", "st": 1, "cs": 0.6, "protect": "Beaver"}, {"page": "https://lite.ria.ru", "st": 0, "cs": 0, "protect": null}, {"page": "https://gosstandart.gov.by", "st": 0, "cs": 0, "protect": null}, {"page": "https://www.dom.gosuslugi.ru", "st": 0, "cs": 0, "protect": null}, {"page": "https://mchs.gov.by", "st": 1, "cs": 0.12, "protect": "nginx"}, {"page": "http://www.prokuratura.gov.by", "st": 1, "cs": 0.6, "protect": "Beaver"}, {"page": "http://www.house.gov.by", "st": 1, "cs": 5.64, "protect": "cloudflare"}, {"page": "http://www.bellegprom.by", "st": 1, "cs": 5.65, "protect": "cloudflare"}, {"page": "http://grodno-region.gov.by/ru", "st": 1, "cs": 0.6, "protect": "Beaver"}, {"page": "https://cdnn1.img.crimea.ria.ru", "st": 0, "cs": 0, "protect": null}, {"page": "https://www.ria.ru", "st": 0, "cs": 0, "protect": null}, {"page": "https://m.ria.ru", "st": 0, "cs": 0, "protect": null}, {"page": "https://bb.gosuslugi.ru", "st": 0, "cs": 0, "protect": null}, {"page": "http://www.kgk.gov.by/ru", "st": 1, "cs": 5.64, "protect": "cloudflare"}, {"page": "https://eln.gosuslugi.ru", "st": 0, "cs": 0, "protect": null}, {"page": "https://sudexpert.gov.by/ru/index.html", "st": 0, "cs": 0, "protect": null}, {"page": "https://propusk.gosuslugi.ru", "st": 0, "cs": 0, "protect": null}, {"page": "https://im.gosuslugi.ru", "st": 0, "cs": 0, "protect": null}, {"page": "https://cdn1.img.ria.ru", "st": 0, "cs": 0, "protect": null}, {"page": "https://cdn23.img.ria.ru", "st": 1, "cs": 0.0, "protect": "nginx"}, {"page": "http://sk.gov.by/ru", "st": 1, "cs": 5.62, "protect": "cloudflare"}, {"page": "https://belnotary.by", "st": 0, "cs": 0, "protect": null}, {"page": "http://www.mst.by", "st": 1, "cs": 5.63, "protect": "cloudflare"}, {"page": "https://www.mil.by", "st": 0, "cs": 0, "protect": null}, {"page": "http://brest-region.gov.by", "st": 1, "cs": 5.65, "protect": "cloudflare"}, {"page": "http://audio1.video.ria.ru", "st": 1, "cs": 28.79, "protect": "nginx/1.18.0 (Ubuntu)"}, {"page": "http://kremlin.ru", "st": 1, "cs": 5.63, "protect": "cloudflare"}, {"page": "https://fileria2.ria.ru", "st": 0, "cs": 0, "protect": null}, {"page": "https://fc.gosuslugi.ru", "st": 0, "cs": 0, "protect": null}, {"page": "https://bgp.by/ru", "st": 0, "cs": 0, "protect": null}, {"page": "https://video.ria.ru", "st": 0, "cs": 0, "protect": null}, {"page": "https://dc.ria.ru", "st": 1, "cs": 0.12, "protect": "QRATOR"}, {"page": "http://minjust.gov.by", "st": 1, "cs": 5.64, "protect": "cloudflare"}, {"page": "https://oac.gov.by", "st": 0, "cs": 0, "protect": null}, {"page": "https://cdnmfd.img.ria.ru", "st": 0, "cs": 0, "protect": null}, {"page": "https://mil.ru", "st": 0, "cs": 0, "protect": null}, {"page": "http://www.gtb.by", "st": 1, "cs": 5.63, "protect": "cloudflare"}, {"page": "http://www.court.by", "st": 1, "cs": 5.63, "protect": "cloudflare"}, {"page": "https://president.gov.by/ru", "st": 0, "cs": 0, "protect": null}, {"page": "https://cdn2.img.ria.ru", "st": 0, "cs": 0, "protect": null}, {"page": "http://www.government.by", "st": 1, "cs": 5.65, "protect": "cloudflare"}, {"page": "https://mobiz.gosuslugi.ru", "st": 0, "cs": 0, "protect": null}, {"page": "http://government.ru", "st": 1, "cs": 0, "protect": "nginx/1.20.1"}, {"page": "https://mintrud.gov.by", "st": 0, "cs": 0, "protect": null}, {"page": "http://www.mas.gov.by", "st": 1, "cs": 0.6, "protect": "Beaver"}, {"page": "http://www.kc.gov.by", "st": 1, "cs": 0.6, "protect": "Beaver"}, {"page": "https://realty.ria.ru", "st": 0, "cs": 0, "protect": null}, {"page": "https://cloud.rkn.gov.ru", "st": 0, "cs": 0, "protect": null}, {"page": "https://mosreg.ru", "st": 0, "cs": 0, "protect": null}, {"page": "https://www.rco.by", "st": 0, "cs": 0, "protect": null}, {"page": "http://www.court.gov.by", "st": 1, "cs": 0.6, "protect": "Beaver"}, {"page": "https://mintrud.gov.by/ru", "st": 0, "cs": 0, "protect": null}, {"page": "https://gosbar.gosuslugi.ru", "st": 0, "cs": 0, "protect": null}, {"page": "https://knd.gosuslugi.ru", "st": 0, "cs": 0, "protect": null}, {"page": "https://www.mvd.gov.by/ru", "st": 0, "cs": 0, "protect": null}, {"page": "http://minenergo.gov.by", "st": 1, "cs": 0.6, "protect": "Beaver"}, {"page": "http://img.lab.ria.ru", "st": 1, "cs": 0.6, "protect": "Beaver"}, {"page": "https://deg.gosuslugi.ru", "st": 0, "cs": 0, "protect": null}, {"page": "http://smev3.gosuslugi.ru", "st": 1, "cs": 0.6, "protect": "Beaver"}, {"page": "https://tr.ria.ru", "st": 0, "cs": 0, "protect": null}, {"page": "https://dom.gosuslugi.ru", "st": 0, "cs": 0, "protect": null}, {"page": "https://www.belneftekhim.by", "st": 0, "cs": 0, "protect": null}, {"page": "https://www.mshp.gov.by", "st": 0, "cs": 0, "protect": null}, {"page": "https://cdnn21.img.ria.ru", "st": 0, "cs": 0, "protect": null}, {"page": "https://invest.gosuslugi.ru", "st": 0, "cs": 0, "protect": null}, {"page": "https://bks.gov.by", "st": 0, "cs": 0, "protect": null}, {"page": "https://www.nalog.gov.ru", "st": 0, "cs": 0, "protect": null}, {"page": "http://mogilev-region.gov.by", "st": 1, "cs": 0.6, "protect": "Beaver"}, {"page": "https://cdn.vd.ria.ru", "st": 0, "cs": 0, "protect": null}, {"page": "https://my.dom.gosuslugi.ru", "st": 0, "cs": 0, "protect": null}, {"page": "https://detsad.gosuslugi.ru", "st": 0, "cs": 0, "protect": null}, {"page": "https://census.gosuslugi.ru", "st": 0, "cs": 0, "protect": null}, {"page": "https://cdnn1.img.ria.ru", "st": 0, "cs": 0, "protect": null}, {"page": "https://img22.ria.ru", "st": 0, "cs": 0, "protect": null}, {"page": "http://pravo.minjust.ru", "st": 1, "cs": 5.64, "protect": "cloudflare"}, {"page": "http://audio2.video.ria.ru", "st": 1, "cs": 0.6, "protect": "Beaver"}, {"page": "https://cbr.ria.ru", "st": 0, "cs": 0, "protect": null}, {"page": "https://www.mart.gov.by", "st": 0, "cs": 0, "protect": null}, {"page": "https://customs.gov.ru", "st": 0, "cs": 0, "protect": null}, {"page": "https://cabinet.ria.ru", "st": 0, "cs": 0, "protect": null}, {"page": "https://web-balancer-main.ria.ru", "st": 0, "cs": 0, "protect": null}, {"page": "https://fileria1.ria.ru", "st": 0, "cs": 0, "protect": null}, {"page": "https://beta.gosuslugi.ru", "st": 0, "cs": 0, "protect": null}, {"page": "http://www.vpk.gov.by", "st": 1, "cs": 0.6, "protect": "Beaver"}, {"page": "http://sk.gov.by", "st": 1, "cs": 0.6, "protect": "Beaver"}, {"page": "https://mail.rkn.gov.ru", "st": 0, "cs": 0, "protect": null}, {"page": "https://che.rus4all.ria.ru", "st": 0, "cs": 0, "protect": null}, {"page": "https://minjust.gov.by", "st": 0, "cs": 0, "protect": null}, {"page": "https://widget.gosuslugi.ru", "st": 0, "cs": 0, "protect": null}, {"page": "http://www.kgk.gov.by", "st": 1, "cs": 5.64, "protect": "cloudflare"}, {"page": "https://mintrans.gov.by", "st": 0, "cs": 0, "protect": null}, {"page": "https://www.mpt.gov.by", "st": 0, "cs": 0, "protect": null}, {"page": "https://pwd.wto.economy.gov.ru", "st": 0, "cs": 0, "protect": null}, {"page": "https://gpk.gov.by", "st": 0, "cs": 0, "protect": null}, {"page": "http://dynamo.by", "st": 1, "cs": 6.08, "protect": "cloudflare"}, {"page": "https://img.crimea.ria.ru", "st": 0, "cs": 0, "protect": null}, {"page": "https://minsk.gov.by", "st": 0, "cs": 0, "protect": null}, {"page": "http://www.nbrb.by", "st": 1, "cs": 5.63, "protect": "cloudflare"}, {"page": "https://portal.gov.by", "st": 0, "cs": 0, "protect": null}, {"page": "http://ds-plugin.gosuslugi.ru", "st": 1, "cs": 0.6, "protect": "Beaver"}, {"page": "http://www.mil.by/ru", "st": 1, "cs": 5.63, "protect": "cloudflare"}, {"page": "http://minzdrav.gov.by/ru", "st": 1, "cs": 5.64, "protect": "cloudflare"}, {"page": "https://pfr.gov.ru", "st": 0, "cs": 0, "protect": null}, {"page": "http://esia.gosuslugi.ru", "st": 1, "cs": 5.65, "protect": "cloudflare"}, {"page": "https://posobie2021.gosuslugi.ru", "st": 0, "cs": 0, "protect": null}, {"page": "http://gosinspekciya.gov.by", "st": 1, "cs": 5.66, "protect": "cloudflare"}, {"page": "https://www.pac.by", "st": 0, "cs": 0, "protect": null}, {"page": "http://gomel-region.gov.by", "st": 1, "cs": 0.6, "protect": "Beaver"}, {"page": "https://mobileapi.ria.ru", "st": 0, "cs": 0, "protect": null}, {"page": "https://www.belarus.by", "st": 0, "cs": 0, "protect": null}, {"page": "http://www.mfa.gov.by", "st": 1, "cs": 5.64, "protect": "cloudflare"}]}